fwt/__init__.py
fwt/authority.py
fwt/serialization.py
fwt-1.0.0.dist-info/licenses/LICENSE
fwt-1.0.0.dist-info/METADATA
fwt-1.0.0.dist-info/WHEEL
fwt-1.0.0.dist-info/top_level.txt
fwt-1.0.0.dist-info/RECORD
