Metadata-Version: 2.4
Name: fwt
Version: 1.0.0
Summary: Fernet (symmetrically signed and encrypted) Web Tokens
Author-email: Sam Santi <redshadow@hackzine.org>
License-Expression: BSD-3-Clause
Project-URL: Homepage, https://github.com/rshk/python-fwt
Project-URL: Repository, https://github.com/rshk/python-fwt
Project-URL: Issues, https://github.com/rshk/python-fwt/issues
Requires-Python: >=3.12
License-File: LICENSE
Requires-Dist: cryptography>=45.0.7
Dynamic: license-file
